TrollHunter/loggers/InfluxLog.py
TrollHunter/loggers/__init__.py
TrollHunter/news_crawler/__init__.py
TrollHunter/news_crawler/news_entry.py
TrollHunter/news_crawler/database/SitemapInfoGetter.py
TrollHunter/news_crawler/database/__init__.py
TrollHunter/news_crawler/database/postgres_database.py
TrollHunter/news_crawler/database/update_database.py
TrollHunter/news_crawler/sitemap/__init__.py
TrollHunter/news_crawler/sitemap/data_elastic.py
TrollHunter/news_crawler/sitemap/keyword_article.py
TrollHunter/news_crawler/sitemap/sitemap.py
TrollHunter/texto/Keyword.py
TrollHunter/texto/Sentiment.py
TrollHunter/texto/__init__.py
TrollHunter/texto/indicator_average.py
TrollHunter/texto/parser_csv.py
TrollHunter/twitter_crawler/__init__.py
TrollHunter/twitter_crawler/api.py
TrollHunter/twitter_crawler/celeryapp.py
TrollHunter/twitter_crawler/crawler.py
TrollHunter/twitter_crawler/twint/twint/__init__.py
TrollHunter/twitter_crawler/twint/twint/cli.py
TrollHunter/twitter_crawler/twint/twint/config.py
TrollHunter/twitter_crawler/twint/twint/datelock.py
TrollHunter/twitter_crawler/twint/twint/feed.py
TrollHunter/twitter_crawler/twint/twint/format.py
TrollHunter/twitter_crawler/twint/twint/get.py
TrollHunter/twitter_crawler/twint/twint/output.py
TrollHunter/twitter_crawler/twint/twint/run.py
TrollHunter/twitter_crawler/twint/twint/tweet.py
TrollHunter/twitter_crawler/twint/twint/url.py
TrollHunter/twitter_crawler/twint/twint/user.py
TrollHunter/twitter_crawler/twint/twint/verbose.py
TrollHunter/twitter_crawler/twint/twint/storage/__init__.py
TrollHunter/twitter_crawler/twint/twint/storage/db.py
TrollHunter/twitter_crawler/twint/twint/storage/elasticsearch.py
TrollHunter/twitter_crawler/twint/twint/storage/panda.py
TrollHunter/twitter_crawler/twint/twint/storage/write.py
TrollHunter/twitter_crawler/twint/twint/storage/write_meta.py
TrollHunter/twitter_crawler/twint_api/__init__.py
TrollHunter/twitter_crawler/twint_api/elastic.py
TrollHunter-0.3.5.dist-info/LICENSE
TrollHunter-0.3.5.dist-info/METADATA
TrollHunter-0.3.5.dist-info/WHEEL
TrollHunter-0.3.5.dist-info/top_level.txt
TrollHunter-0.3.5.dist-info/RECORD
